README.md
setup.cfg
setup.py
sams_client/__init__.py
sams_client/client.py
sams_client/constants.py
sams_client/default_settings.py
sams_client/errors.py
sams_client/utils.py
sams_client.egg-info/PKG-INFO
sams_client.egg-info/SOURCES.txt
sams_client.egg-info/dependency_links.txt
sams_client.egg-info/requires.txt
sams_client.egg-info/top_level.txt
sams_client/auth/__init__.py
sams_client/auth/basic.py
sams_client/auth/public.py
sams_client/endpoints/__init__.py
sams_client/endpoints/assets.py
sams_client/endpoints/endpoint.py
sams_client/endpoints/images.py
sams_client/endpoints/sets.py
sams_client/endpoints/storage_destinations.py
sams_client/schemas/__init__.py
sams_client/schemas/assets.py
sams_client/schemas/destinations.py
sams_client/schemas/sets.py