Metadata-Version: 2.1
Name: sams-client
Version: 0.3.0
Summary: Super Asset Management Service Client
Home-page: https://github.com/superdesk/sams
Author: Tanuj Soni
Author-email: tanuj.soni@sourcefabric.org
License: AGPLv3
Platform: any
Classifier: Development Status :: 5 - Production/Stable
Classifier: Environment :: Console
Classifier: Intended Audience :: Developers
Classifier: Intended Audience :: Information Technology
Classifier: Intended Audience :: System Administrators
Classifier: License :: OSI Approved :: GNU Affero General Public License v3
Classifier: Operating System :: OS Independent
Classifier: Programming Language :: Python
Classifier: Programming Language :: Python :: 3
Classifier: Programming Language :: Python :: 3.6
Classifier: Topic :: Database
Classifier: Topic :: Internet :: WWW/HTTP :: Dynamic Content
Classifier: Topic :: Internet :: WWW/HTTP :: WSGI :: Application
Classifier: Topic :: Multimedia
Requires-Python: ~=3.6
